<?xml version="1.0" encoding="utf-8" ?><dwsync><file name="ascci-logo.gif" server="ftp.monkeyzbox.com" local="3239132400" remote="63558529724" /><file name="destaque-1.jpg" server="ftp.monkeyzbox.com" local="3239132400" remote="63558529724" /><file name="destaque-2.jpg" server="ftp.monkeyzbox.com" local="3239132400" remote="63558529724" /><file name="destaque-3.jpg" server="ftp.monkeyzbox.com" local="3239132400" remote="63558529724" /><file name="destaque-4.jpg" server="ftp.monkeyzbox.com" local="3239132400" remote="63558529724" /><file name="destaque-5.jpg" server="ftp.monkeyzbox.com" local="3239132400" remote="63558529724" /><file name="destaque-6.jpg" server="ftp.monkeyzbox.com" local="3239132400" remote="63558529724" /><file name="destaque-thumb-1.jpg" server="ftp.monkeyzbox.com" local="3239132400" remote="89328333500" /><file name="destaque-thumb-2.jpg" server="ftp.monkeyzbox.com" local="3239132400" remote="89328333500" /><file name="destaque-thumb-3.jpg" server="ftp.monkeyzbox.com" local="3239132400" remote="89328333500" /><file name="destaque-thumb-4.jpg" server="ftp.monkeyzbox.com" local="3239132400" remote="89328333500" /><file name="destaque-thumb-5.jpg" server="ftp.monkeyzbox.com" local="3239132400" remote="89328333500" /><file name="destaque-thumb-6.jpg" server="ftp.monkeyzbox.com" local="3239132400" remote="89328333500" /><file name="dicaLivro-01.jpg" server="ftp.monkeyzbox.com" local="3239132400" remote="72148464316" /><file name="lucci-logo.gif" server="ftp.monkeyzbox.com" local="3239132400" remote="63558529724" /><file name="models.jpg" server="ftp.monkeyzbox.com" local="3239132400" remote="46378660540" /><file name="newsCol-bk.gif" server="ftp.monkeyzbox.com" local="3239132400" remote="63558529724" /><file name="s-room-01-large.jpg" server="ftp.monkeyzbox.com" local="3239132400" remote="85033366204" /><file name="s-room-01.jpg" server="ftp.monkeyzbox.com" local="3239132400" remote="59263562428" /><file name="s-room-02-large.jpg" server="ftp.monkeyzbox.com" local="3239132400" remote="85033366204" /><file name="s-room-02.jpg" server="ftp.monkeyzbox.com" local="3239132400" remote="59263562428" /><file name="s-room-03-large.jpg" server="ftp.monkeyzbox.com" local="3239132400" remote="85033366204" /><file name="s-room-03.jpg" server="ftp.monkeyzbox.com" local="3239132400" remote="59263562428" /><file name="s-room-04-large.jpg" server="ftp.monkeyzbox.com" local="3239132400" remote="85033366204" /><file name="s-room-04.jpg" server="ftp.monkeyzbox.com" local="3239132400" remote="59263562428" /><file name="s-room-05-large.jpg" server="ftp.monkeyzbox.com" local="3239132400" remote="85033366204" /><file name="s-room-05.jpg" server="ftp.monkeyzbox.com" local="3239132400" remote="59263562428" /><file name="s-room-06-large.jpg" server="ftp.monkeyzbox.com" local="3239132400" remote="85033366204" /><file name="s-room-06.jpg" server="ftp.monkeyzbox.com" local="3239132400" remote="59263562428" /><file name="vizu-logo.gif" server="ftp.monkeyzbox.com" local="3239132400" remote="59263562428" /><file name="vizu291.jpg" server="ftp.monkeyzbox.com" local="3239132400" remote="50673627836" /></dwsync>